{
  "packageId": "com.fivefifthsvoter.www.twa",
  "host": "www.fivefifthsvoter.com",
  "name": "Five Fifths Voter",
  "launcherName": "Five Fifths",
  "display": "standalone",
  "themeColor": "#000000",
  "navigationColor": "#000000",
  "navigationColorDark": "#000000",
  "navigationDividerColor": "#000000",
  "navigationDividerColorDark": "#000000",
  "backgroundColor": "#000000",
  "enableNotifications": true,
  "startUrl": "/",
  "iconUrl": "https://www.fivefifthsvoter.com/img/icons/android-chrome-512x512.png",
  "maskableIconUrl": "https://www.fivefifthsvoter.com/img/icons/android-chrome-maskable-512x512.png",
  "splashScreenFadeOutDuration": 300,
  "signingKey": {
    "path": "/Users/upkar/Documents/upkar-code/android/android.keystore",
    "alias": "android"
  },
  "appVersionName": "1",
  "appVersionCode": 1,
  "shortcuts": [],
  "generatorApp": "bubblewrap-cli",
  "webManifestUrl": "https://www.fivefifthsvoter.com/manifest.json",
  "fallbackType": "customtabs",
  "features": {},
  "alphaDependencies": {
    "enabled": false
  },
  "enableSiteSettingsShortcut": true,
  "isChromeOSOnly": false,
  "orientation": "default",
  "fingerprints": [],
  "additionalTrustedOrigins": [],
  "appVersion": "1"
}